aws_lambda_context/__init__.py
aws_lambda_context/py.typed
aws_lambda_context-1.1.0.dist-info/LICENSE
aws_lambda_context-1.1.0.dist-info/METADATA
aws_lambda_context-1.1.0.dist-info/WHEEL
aws_lambda_context-1.1.0.dist-info/top_level.txt
aws_lambda_context-1.1.0.dist-info/RECORD
