Metadata-Version: 2.1
Name: aws-lambda-context
Version: 1.1.0
Summary: AWS Lambda Context class for type checking and testing
Home-page: https://gitlab.com/new10-public/python-lambda-context
Author: New10 B.V.
Author-email: pypi-admin@new10.com
License: UNKNOWN
Platform: UNKNOWN
Classifier: Development Status :: 5 - Production/Stable
Classifier: Programming Language :: Python :: 3
Classifier: Programming Language :: Python :: 3.6
Classifier: Programming Language :: Python :: 3.7
Classifier: License :: OSI Approved :: MIT License
Requires-Python: >= 3.6
Provides-Extra: tests
